{
  "project_info": {
    "project_number": "844508327926",
    "project_id": "konne-e976f",
    "storage_bucket": "konne-e976f.appspot.com"
  },
  "client": [
    {
      "client_info": {
        "mobilesdk_app_id": "1:844508327926:android:3e42f0295dc965a34aa1d7",
        "android_client_info": {
          "package_name": "com.example.konne_seller"
        }
      },
      "oauth_client": [],
      "api_key": [
        {
          "current_key": "AIzaSyBkDAcOBEYA4VdUu9cIH5elWqyQuS9zTL0"
        }
      ],
      "services": {
        "appinvite_service": {
          "other_platform_oauth_client": []
        }
      }
    },
    {
      "client_info": {
        "mobilesdk_app_id": "1:844508327926:android:141866a53bfd18954aa1d7",
        "android_client_info": {
          "package_name": "com.example.konne_sp"
        }
      },
      "oauth_client": [],
      "api_key": [
        {
          "current_key": "AIzaSyBkDAcOBEYA4VdUu9cIH5elWqyQuS9zTL0"
        }
      ],
      "services": {
        "appinvite_service": {
          "other_platform_oauth_client": []
        }
      }
    }
  ],
  "configuration_version": "1"
}